Workbook

Sheet 00_RESUMEN
A1: EXPEDIENTE FISCAL — RESIDENTE (AUTÓNOMO / PYME)
A3: DATOS DEL CLIENTE | D3: RESUMEN DEL EJERCICIO
A4: Nombre / razón social | D4: Ejercicio seleccionado | E4: 2026 | G4: TOTAL A INGRESAR | H4: =E11+E12+E13
A5: NIF | D5: Actividad (IAE) | E5: =IFERROR(INDEX('01_ACTIVIDAD'!$C$2:$C$200,MATCH("*",'01_ACTIVIDAD'!$C$2:$C$200,0)),"") | G5: Facturas emitidas | H5: =COUNTIFS('02_FACTURAS_EMITIDAS'!$B$2:$B$3000,$E$4)
A6: Tipo de cliente | D6: Régimen IVA | E6: =IFERROR(INDEX('01_ACTIVIDAD'!$E$2:$E$200,MATCH("*",'01_ACTIVIDAD'!$E$2:$E$200,0)),"") | G6: Facturas recibidas | H6: =COUNTIFS('03_FACTURAS_RECIBIDAS'!$B$2:$B$3000,$E$4)
A7: Email | D7: Régimen IRPF | E7: =IFERROR(INDEX('01_ACTIVIDAD'!$F$2:$F$200,MATCH("*",'01_ACTIVIDAD'!$F$2:$F$200,0)),"") | G7: Documentos faltantes | H7: =COUNTIF('08_DOCUMENTACION'!$G$2:$G$2000,"Falta")
A8: Teléfono | D8: Ingresos del ejercicio | E8: =SUMIFS('02_FACTURAS_EMITIDAS'!$I$2:$I$3000,'02_FACTURAS_EMITIDAS'!$B$2:$B$3000,$E$4) | G8: Obligaciones pendientes | H8: =COUNTIFS('09_OBLIGACIONES'!$B$2:$B$2000,$E$4,'09_OBLIGACIONES'!$E$2:$E$2000,"Pendiente")
A9: Responsable expediente | D9: Gastos deducibles IRPF | E9: =SUMIFS('03_FACTURAS_RECIBIDAS'!$R$2:$R$3000,'03_FACTURAS_RECIBIDAS'!$B$2:$B$3000,$E$4)
A10: Carpeta cliente / enlace | D10: Rendimiento neto | E10: =E8-E9
A11: Fecha última revisión | D11: IVA a ingresar (303) | E11: =SUMIFS('04_MODELO_303'!$J$2:$J$500,'04_MODELO_303'!$B$2:$B$500,$E$4)
D12: IRPF a ingresar (130) | E12: =SUMIFS('05_MODELO_130'!$K$2:$K$500,'05_MODELO_130'!$B$2:$B$500,$E$4)
D13: Retenciones 111 / 115 | E13: =SUMIFS('06_RETENCIONES_111_115'!$G$2:$G$500,'06_RETENCIONES_111_115'!$B$2:$B$500,$E$4)
A15: RESUMEN TRIMESTRAL
A16: Trimestre | B16: Ingresos | C16: Gastos IRPF | D16: Rendimiento | E16: IVA devengado | F16: IVA deducible | G16: 303 a ingresar | H16: 130 a ingresar
A17: 1T | B17: =SUMIFS('02_FACTURAS_EMITIDAS'!$I$2:$I$3000,'02_FACTURAS_EMITIDAS'!$B$2:$B$3000,$E$4,'02_FACTURAS_EMITIDAS'!$C$2:$C$3000,$A17) | C17: =SUMIFS('03_FACTURAS_RECIBIDAS'!$R$2:$R$3000,'03_FACTURAS_RECIBIDAS'!$B$2:$B$3000,$E$4,'03_FACTURAS_RECIBIDAS'!$C$2:$C$3000,$A17) | D17: =B17-C17 | E17: =SUMIFS('04_MODELO_303'!$E$2:$E$500,'04_MODELO_303'!$B$2:$B$500,$E$4,'04_MODELO_303'!$C$2:$C$500,$A17) | F17: =SUMIFS('04_MODELO_303'!$G$2:$G$500,'04_MODELO_303'!$B$2:$B$500,$E$4,'04_MODELO_303'!$C$2:$C$500,$A17) | G17: =SUMIFS('04_MODELO_303'!$J$2:$J$500,'04_MODELO_303'!$B$2:$B$500,$E$4,'04_MODELO_303'!$C$2:$C$500,$A17) | H17: =SUMIFS('05_MODELO_130'!$K$2:$K$500,'05_MODELO_130'!$B$2:$B$500,$E$4,'05_MODELO_130'!$C$2:$C$500,$A17)
A18: 2T | B18: =SUMIFS('02_FACTURAS_EMITIDAS'!$I$2:$I$3000,'02_FACTURAS_EMITIDAS'!$B$2:$B$3000,$E$4,'02_FACTURAS_EMITIDAS'!$C$2:$C$3000,$A18) | C18: =SUMIFS('03_FACTURAS_RECIBIDAS'!$R$2:$R$3000,'03_FACTURAS_RECIBIDAS'!$B$2:$B$3000,$E$4,'03_FACTURAS_RECIBIDAS'!$C$2:$C$3000,$A18) | D18: =B18-C18 | E18: =SUMIFS('04_MODELO_303'!$E$2:$E$500,'04_MODELO_303'!$B$2:$B$500,$E$4,'04_MODELO_303'!$C$2:$C$500,$A18) | F18: =SUMIFS('04_MODELO_303'!$G$2:$G$500,'04_MODELO_303'!$B$2:$B$500,$E$4,'04_MODELO_303'!$C$2:$C$500,$A18) | G18: =SUMIFS('04_MODELO_303'!$J$2:$J$500,'04_MODELO_303'!$B$2:$B$500,$E$4,'04_MODELO_303'!$C$2:$C$500,$A18) | H18: =SUMIFS('05_MODELO_130'!$K$2:$K$500,'05_MODELO_130'!$B$2:$B$500,$E$4,'05_MODELO_130'!$C$2:$C$500,$A18)
A19: 3T | B19: =SUMIFS('02_FACTURAS_EMITIDAS'!$I$2:$I$3000,'02_FACTURAS_EMITIDAS'!$B$2:$B$3000,$E$4,'02_FACTURAS_EMITIDAS'!$C$2:$C$3000,$A19) | C19: =SUMIFS('03_FACTURAS_RECIBIDAS'!$R$2:$R$3000,'03_FACTURAS_RECIBIDAS'!$B$2:$B$3000,$E$4,'03_FACTURAS_RECIBIDAS'!$C$2:$C$3000,$A19) | D19: =B19-C19 | E19: =SUMIFS('04_MODELO_303'!$E$2:$E$500,'04_MODELO_303'!$B$2:$B$500,$E$4,'04_MODELO_303'!$C$2:$C$500,$A19) | F19: =SUMIFS('04_MODELO_303'!$G$2:$G$500,'04_MODELO_303'!$B$2:$B$500,$E$4,'04_MODELO_303'!$C$2:$C$500,$A19) | G19: =SUMIFS('04_MODELO_303'!$J$2:$J$500,'04_MODELO_303'!$B$2:$B$500,$E$4,'04_MODELO_303'!$C$2:$C$500,$A19) | H19: =SUMIFS('05_MODELO_130'!$K$2:$K$500,'05_MODELO_130'!$B$2:$B$500,$E$4,'05_MODELO_130'!$C$2:$C$500,$A19)
A20: 4T | B20: =SUMIFS('02_FACTURAS_EMITIDAS'!$I$2:$I$3000,'02_FACTURAS_EMITIDAS'!$B$2:$B$3000,$E$4,'02_FACTURAS_EMITIDAS'!$C$2:$C$3000,$A20) | C20: =SUMIFS('03_FACTURAS_RECIBIDAS'!$R$2:$R$3000,'03_FACTURAS_RECIBIDAS'!$B$2:$B$3000,$E$4,'03_FACTURAS_RECIBIDAS'!$C$2:$C$3000,$A20) | D20: =B20-C20 | E20: =SUMIFS('04_MODELO_303'!$E$2:$E$500,'04_MODELO_303'!$B$2:$B$500,$E$4,'04_MODELO_303'!$C$2:$C$500,$A20) | F20: =SUMIFS('04_MODELO_303'!$G$2:$G$500,'04_MODELO_303'!$B$2:$B$500,$E$4,'04_MODELO_303'!$C$2:$C$500,$A20) | G20: =SUMIFS('04_MODELO_303'!$J$2:$J$500,'04_MODELO_303'!$B$2:$B$500,$E$4,'04_MODELO_303'!$C$2:$C$500,$A20) | H20: =SUMIFS('05_MODELO_130'!$K$2:$K$500,'05_MODELO_130'!$B$2:$B$500,$E$4,'05_MODELO_130'!$C$2:$C$500,$A20)
A21: TOTAL | B21: =SUM(B17:B20) | C21: =SUM(C17:C20) | D21: =SUM(D17:D20) | E21: =SUM(E17:E20) | F21: =SUM(F17:F20) | G21: =SUM(G17:G20) | H21: =SUM(H17:H20)
A24: GASTOS DEDUCIBLES POR CATEGORÍA
A25: Categoría | B25: Gasto deducible IRPF | C25: Nº facturas
A26: Compras | B26: =SUMIFS('03_FACTURAS_RECIBIDAS'!$R$2:$R$3000,'03_FACTURAS_RECIBIDAS'!$B$2:$B$3000,$E$4,'03_FACTURAS_RECIBIDAS'!$I$2:$I$3000,$A26) | C26: =COUNTIFS('03_FACTURAS_RECIBIDAS'!$B$2:$B$3000,$E$4,'03_FACTURAS_RECIBIDAS'!$I$2:$I$3000,$A26)
A27: Alquiler local | B27: =SUMIFS('03_FACTURAS_RECIBIDAS'!$R$2:$R$3000,'03_FACTURAS_RECIBIDAS'!$B$2:$B$3000,$E$4,'03_FACTURAS_RECIBIDAS'!$I$2:$I$3000,$A27) | C27: =COUNTIFS('03_FACTURAS_RECIBIDAS'!$B$2:$B$3000,$E$4,'03_FACTURAS_RECIBIDAS'!$I$2:$I$3000,$A27)
A28: Suministros | B28: =SUMIFS('03_FACTURAS_RECIBIDAS'!$R$2:$R$3000,'03_FACTURAS_RECIBIDAS'!$B$2:$B$3000,$E$4,'03_FACTURAS_RECIBIDAS'!$I$2:$I$3000,$A28) | C28: =COUNTIFS('03_FACTURAS_RECIBIDAS'!$B$2:$B$3000,$E$4,'03_FACTURAS_RECIBIDAS'!$I$2:$I$3000,$A28)
A29: Servicios profesionales | B29: =SUMIFS('03_FACTURAS_RECIBIDAS'!$R$2:$R$3000,'03_FACTURAS_RECIBIDAS'!$B$2:$B$3000,$E$4,'03_FACTURAS_RECIBIDAS'!$I$2:$I$3000,$A29) | C29: =COUNTIFS('03_FACTURAS_RECIBIDAS'!$B$2:$B$3000,$E$4,'03_FACTURAS_RECIBIDAS'!$I$2:$I$3000,$A29)
A30: Seguros | B30: =SUMIFS('03_FACTURAS_RECIBIDAS'!$R$2:$R$3000,'03_FACTURAS_RECIBIDAS'!$B$2:$B$3000,$E$4,'03_FACTURAS_RECIBIDAS'!$I$2:$I$3000,$A30) | C30: =COUNTIFS('03_FACTURAS_RECIBIDAS'!$B$2:$B$3000,$E$4,'03_FACTURAS_RECIBIDAS'!$I$2:$I$3000,$A30)
A31: Seguridad Social | B31: =SUMIFS('03_FACTURAS_RECIBIDAS'!$R$2:$R$3000,'03_FACTURAS_RECIBIDAS'!$B$2:$B$3000,$E$4,'03_FACTURAS_RECIBIDAS'!$I$2:$I$3000,$A31) | C31: =COUNTIFS('03_FACTURAS_RECIBIDAS'!$B$2:$B$3000,$E$4,'03_FACTURAS_RECIBIDAS'!$I$2:$I$3000,$A31)
A32: Material de oficina | B32: =SUMIFS('03_FACTURAS_RECIBIDAS'!$R$2:$R$3000,'03_FACTURAS_RECIBIDAS'!$B$2:$B$3000,$E$4,'03_FACTURAS_RECIBIDAS'!$I$2:$I$3000,$A32) | C32: =COUNTIFS('03_FACTURAS_RECIBIDAS'!$B$2:$B$3000,$E$4,'03_FACTURAS_RECIBIDAS'!$I$2:$I$3000,$A32)
A33: Reparación/conservación | B33: =SUMIFS('03_FACTURAS_RECIBIDAS'!$R$2:$R$3000,'03_FACTURAS_RECIBIDAS'!$B$2:$B$3000,$E$4,'03_FACTURAS_RECIBIDAS'!$I$2:$I$3000,$A33) | C33: =COUNTIFS('03_FACTURAS_RECIBIDAS'!$B$2:$B$3000,$E$4,'03_FACTURAS_RECIBIDAS'!$I$2:$I$3000,$A33)
A34: Publicidad | B34: =SUMIFS('03_FACTURAS_RECIBIDAS'!$R$2:$R$3000,'03_FACTURAS_RECIBIDAS'!$B$2:$B$3000,$E$4,'03_FACTURAS_RECIBIDAS'!$I$2:$I$3000,$A34) | C34: =COUNTIFS('03_FACTURAS_RECIBIDAS'!$B$2:$B$3000,$E$4,'03_FACTURAS_RECIBIDAS'!$I$2:$I$3000,$A34)
A35: Viajes y transporte | B35: =SUMIFS('03_FACTURAS_RECIBIDAS'!$R$2:$R$3000,'03_FACTURAS_RECIBIDAS'!$B$2:$B$3000,$E$4,'03_FACTURAS_RECIBIDAS'!$I$2:$I$3000,$A35) | C35: =COUNTIFS('03_FACTURAS_RECIBIDAS'!$B$2:$B$3000,$E$4,'03_FACTURAS_RECIBIDAS'!$I$2:$I$3000,$A35)
A36: Comisiones bancarias | B36: =SUMIFS('03_FACTURAS_RECIBIDAS'!$R$2:$R$3000,'03_FACTURAS_RECIBIDAS'!$B$2:$B$3000,$E$4,'03_FACTURAS_RECIBIDAS'!$I$2:$I$3000,$A36) | C36: =COUNTIFS('03_FACTURAS_RECIBIDAS'!$B$2:$B$3000,$E$4,'03_FACTURAS_RECIBIDAS'!$I$2:$I$3000,$A36)
A37: Otros | B37: =SUMIFS('03_FACTURAS_RECIBIDAS'!$R$2:$R$3000,'03_FACTURAS_RECIBIDAS'!$B$2:$B$3000,$E$4,'03_FACTURAS_RECIBIDAS'!$I$2:$I$3000,$A37) | C37: =COUNTIFS('03_FACTURAS_RECIBIDAS'!$B$2:$B$3000,$E$4,'03_FACTURAS_RECIBIDAS'!$I$2:$I$3000,$A37)
A38: TOTAL | B38: =SUM(B26:B37) | C38: =SUM(C26:C37)
A40: Detalle y PDF de cada factura en 02_FACTURAS_EMITIDAS y 03_FACTURAS_RECIBIDAS (columna de enlace).

Sheet 01_ACTIVIDAD
A1: ID_ACTIVIDAD | B1: Fecha alta | C1: Epígrafe IAE | D1: Descripción actividad | E1: Régimen IVA | F1: Régimen IRPF | G1: Modelos (036/037) | H1: ¿Obligado al 130? | I1: Fecha baja | J1: Ruta / enlace 036 | K1: Observaciones

Sheet 02_FACTURAS_EMITIDAS
A1: ID_FACTURA | B1: Ejercicio | C1: Trimestre | D1: Fecha factura | E1: Nº factura | F1: Cliente / receptor | G1: NIF cliente | H1: Concepto | I1: Base imponible | J1: % IVA | K1: Cuota IVA | L1: % retención IRPF | M1: Retención IRPF | N1: Total factura | O1: Estado cobro | P1: Ruta / enlace PDF | Q1: Observaciones
N2: =IF(A2="","",I2+K2-M2)
N3: =IF(A3="","",I3+K3-M3)
N4: =IF(A4="","",I4+K4-M4)
N5: =IF(A5="","",I5+K5-M5)
N6: =IF(A6="","",I6+K6-M6)
N7: =IF(A7="","",I7+K7-M7)
N8: =IF(A8="","",I8+K8-M8)
N9: =IF(A9="","",I9+K9-M9)
N10: =IF(A10="","",I10+K10-M10)
N11: =IF(A11="","",I11+K11-M11)
N12: =IF(A12="","",I12+K12-M12)
N13: =IF(A13="","",I13+K13-M13)
... N400: =IF(A400="","",I400+K400-M400)

Sheet 03_FACTURAS_RECIBIDAS
A1: ID_FACTURA | B1: Ejercicio | C1: Trimestre | D1: Fecha factura | E1: Nº factura | F1: Proveedor | G1: NIF proveedor | H1: Concepto | I1: Categoría gasto | J1: Base imponible | K1: % IVA | L1: Cuota IVA | M1: % IVA deducible | N1: % retención | O1: Retención practicada | P1: Total factura | Q1: % deducible IRPF | R1: Gasto deducible IRPF | S1: Ruta / enlace PDF | T1: Observaciones
P2: =IF(A2="","",J2+L2-O2) | R2: =IF(A2="","",(J2+L2*(1-IF(M2="",1,M2)))*IF(Q2="",1,Q2))
P3: =IF(A3="","",J3+L3-O3) | R3: =IF(A3="","",(J3+L3*(1-IF(M3="",1,M3)))*IF(Q3="",1,Q3))
P4: =IF(A4="","",J4+L4-O4) | R4: =IF(A4="","",(J4+L4*(1-IF(M4="",1,M4)))*IF(Q4="",1,Q4))
P5: =IF(A5="","",J5+L5-O5) | R5: =IF(A5="","",(J5+L5*(1-IF(M5="",1,M5)))*IF(Q5="",1,Q5))
P6: =IF(A6="","",J6+L6-O6) | R6: =IF(A6="","",(J6+L6*(1-IF(M6="",1,M6)))*IF(Q6="",1,Q6))
P7: =IF(A7="","",J7+L7-O7) | R7: =IF(A7="","",(J7+L7*(1-IF(M7="",1,M7)))*IF(Q7="",1,Q7))
P8: =IF(A8="","",J8+L8-O8) | R8: =IF(A8="","",(J8+L8*(1-IF(M8="",1,M8)))*IF(Q8="",1,Q8))
P9: =IF(A9="","",J9+L9-O9) | R9: =IF(A9="","",(J9+L9*(1-IF(M9="",1,M9)))*IF(Q9="",1,Q9))
P10: =IF(A10="","",J10+L10-O10) | R10: =IF(A10="","",(J10+L10*(1-IF(M10="",1,M10)))*IF(Q10="",1,Q10))
P11: =IF(A11="","",J11+L11-O11) | R11: =IF(A11="","",(J11+L11*(1-IF(M11="",1,M11)))*IF(Q11="",1,Q11))
P12: =IF(A12="","",J12+L12-O12) | R12: =IF(A12="","",(J12+L12*(1-IF(M12="",1,M12)))*IF(Q12="",1,Q12))
P13: =IF(A13="","",J13+L13-O13) | R13: =IF(A13="","",(J13+L13*(1-IF(M13="",1,M13)))*IF(Q13="",1,Q13))
... P400: =IF(A400="","",J400+L400-O400) | R400: =IF(A400="","",(J400+L400*(1-IF(M400="",1,M400)))*IF(Q400="",1,Q400))

Sheet 04_MODELO_303
A1: ID_303 | B1: Ejercicio | C1: Trimestre | D1: Base IVA devengado | E1: IVA devengado | F1: Base IVA deducible | G1: IVA deducible | H1: A compensar de periodos anteriores | I1: Resultado | J1: A ingresar | K1: A compensar | L1: Estado | M1: Fecha presentación | N1: NRC / justificante | O1: Ruta / enlace PDF | P1: Observaciones

Sheet 05_MODELO_130
A1: ID_130 | B1: Ejercicio | C1: Trimestre | D1: Ingresos acumulados | E1: Gastos acumulados | F1: Rendimiento neto | G1: 20 % del rendimiento | H1: Retenciones acumuladas | I1: Pagos 130 anteriores | J1: Resultado | K1: A ingresar | L1: Estado | M1: Fecha presentación | N1: NRC / justificante | O1: Ruta / enlace PDF | P1: Observaciones

Sheet 06_RETENCIONES_111_115
A1: ID_RETENCION | B1: Ejercicio | C1: Trimestre | D1: Modelo | E1: Nº perceptores | F1: Base retenciones | G1: Retenciones | H1: Estado | I1: Fecha presentación | J1: NRC / justificante | K1: Ruta / enlace PDF | L1: Observaciones

Sheet 07_MODELOS_PRESENTADOS
A1: ID_MODELO | B1: Modelo | C1: Ejercicio | D1: Periodo | E1: Fecha presentación | F1: Importe ingresado | G1: CSV / NRC | H1: Estado | I1: Ruta / enlace PDF | J1: Observaciones

Sheet 08_DOCUMENTACION
A1: ID_DOC | B1: ID_INMUEBLE | C1: ID_CONTRATO | D1: Ejercicio | E1: Tipo documento | F1: Descripción | G1: Estado documento | H1: Fecha documento | I1: Fecha caducidad | J1: Ruta / enlace | K1: Última revisión | L1: Observaciones

Sheet 09_OBLIGACIONES
A1: ID_OBLIGACION | B1: Ejercicio | C1: Tipo obligación | D1: ID_INMUEBLE | E1: Estado | F1: Fecha límite | G1: Fecha presentación | H1: Importe pagado | I1: Documentación faltante | J1: ID modelo asociado | K1: Notas

Sheet 10_NOTAS
A1: ID_NOTA | B1: Fecha | C1: Categoría | D1: Asunto | E1: Nota / incidencia | F1: Próxima acción | G1: Fecha próxima acción | H1: Responsable

Sheet 11_COMO_USAR
A1: CÓMO MANTENER EL EXPEDIENTE DEL RESIDENTE (AUTÓNOMO / PYME)
A3: PASO | B3: ACCIÓN
A4: 1 | B4: Suelta el modelo 036/037 en la carpeta _ARRASTRA_AQUI: fija actividad, régimen de IVA/IRPF y modelos.
A5: 2 | B5: Suelta las facturas emitidas y recibidas: la app las clasifica, rellena 02/03 y guarda el PDF.
A6: 3 | B6: Revisa la categoría y los % deducibles de las facturas recibidas (columnas I, M y Q).
A7: 4 | B7: Las hojas 04 (303), 05 (130) y 06 (111/115) se recalculan solas cada trimestre.
A8: 5 | B8: Al presentar un modelo, márcalo «Presentado» (o suelta el justificante): esa fila queda congelada.
A9: 6 | B9: Los importes en blanco de las columnas con fórmula no se escriben a mano.
A10: 7 | B10: Lo marcado VERIFICAR en observaciones requiere criterio del asesor.
